corte/__init__.py
corte/batch_processor.py
corte/cli.py
corte/llm_client.py
corte/pdf_processor.py
corte-0.1.0.dist-info/licenses/LICENSE
corte-0.1.0.dist-info/METADATA
corte-0.1.0.dist-info/WHEEL
corte-0.1.0.dist-info/entry_points.txt
corte-0.1.0.dist-info/top_level.txt
corte-0.1.0.dist-info/RECORD
