Metadata-Version: 2.4
Name: corte
Version: 0.1.0
Summary: A tool to cut PDFs into pieces and process them with LLMs in batches
Author-email: Your Name <your.email@example.com>
License: MIT
Project-URL: Homepage, https://github.com/yourusername/corte
Project-URL: Repository, https://github.com/yourusername/corte
Project-URL: Documentation, https://github.com/yourusername/corte#readme
Project-URL: Bug Tracker, https://github.com/yourusername/corte/issues
Keywords: pdf,llm,processing,batch,ai
Classifier: Development Status :: 3 - Alpha
Classifier: Intended Audience :: Developers
Classifier: License :: OSI Approved :: MIT License
Classifier: Programming Language :: Python :: 3
Classifier: Programming Language :: Python :: 3.8
Classifier: Programming Language :: Python :: 3.9
Classifier: Programming Language :: Python :: 3.10
Classifier: Programming Language :: Python :: 3.11
Classifier: Programming Language :: Python :: 3.12
Classifier: Topic :: Software Development :: Libraries :: Python Modules
Classifier: Topic :: Text Processing
Classifier: Topic :: Scientific/Engineering :: Artificial Intelligence
Requires-Python: >=3.8
License-File: LICENSE
Requires-Dist: PyPDF2>=3.0.0
Requires-Dist: click>=8.0.0
Requires-Dist: openai>=1.0.0
Requires-Dist: anthropic>=0.20.0
Requires-Dist: requests>=2.25.0
Requires-Dist: python-dotenv>=0.19.0
Provides-Extra: dev
Requires-Dist: pytest>=7.0.0; extra == "dev"
Requires-Dist: pytest-cov>=4.0.0; extra == "dev"
Requires-Dist: black>=22.0.0; extra == "dev"
Requires-Dist: flake8>=5.0.0; extra == "dev"
Requires-Dist: mypy>=1.0.0; extra == "dev"
Requires-Dist: pre-commit>=2.20.0; extra == "dev"
Provides-Extra: langchain
Requires-Dist: langchain>=0.2.0; extra == "langchain"
Requires-Dist: langchain-openai>=0.1.0; extra == "langchain"
Requires-Dist: langchain-anthropic>=0.1.0; extra == "langchain"
Requires-Dist: langchain-google-genai>=1.0.0; extra == "langchain"
Requires-Dist: langchain-community>=0.2.0; extra == "langchain"
Provides-Extra: all
Requires-Dist: corte[dev,langchain]; extra == "all"
Dynamic: license-file
